kosopy/__init__.py
kosopy/cli.py
kosopy/kosopy.py
kosopy/wlbinary.py
kosopy-0.0.3.dist-info/LICENSE
kosopy-0.0.3.dist-info/METADATA
kosopy-0.0.3.dist-info/WHEEL
kosopy-0.0.3.dist-info/entry_points.txt
kosopy-0.0.3.dist-info/top_level.txt
kosopy-0.0.3.dist-info/RECORD
