Metadata-Version: 2.1
Name: kosopy
Version: 0.0.3
Summary: A python pacakge to handle KoSO data.
Author-email: Bibhuti Kumar Jha <bibhuraushan1@gmail.com>
License: MIT License
Project-URL: Homepage, https://github.com/Kodaikanal-Solar-Observatory/kosopy
Keywords: kosopy
Classifier: Intended Audience :: Developers
Classifier: License :: OSI Approved :: MIT License
Classifier: Natural Language :: English
Classifier: Programming Language :: Python :: 3.8
Classifier: Programming Language :: Python :: 3.9
Classifier: Programming Language :: Python :: 3.10
Classifier: Programming Language :: Python :: 3.11
Classifier: Programming Language :: Python :: 3.12
Requires-Python: >=3.8
License-File: LICENSE
Requires-Dist: numpy
Provides-Extra: all
Requires-Dist: kosopy[extra] ; extra == 'all'
Provides-Extra: extra
Requires-Dist: pandas ; extra == 'extra'
